{
  "url": "https://www.hooktheory.com/theorytab/view/ezra-furman/rated-r-crusaders",
  "title": "Rated R Crusaders by Ezra Furman Chords, Melody, and Music Theory Analysis - Hooktheory",
  "sections": [
    {
      "name": "Verse",
      "hash": "#verse",
      "songId": "RPxeJbLqob_",
      "containerId": "tab-RPxeJbLqob_",
      "renderedCount": 12,
      "jsonChordCount": 16,
      "jsonNonRestCount": 12,
      "json": {
        "songId": 1347313,
        "songInfo": "Rated R Crusaders",
        "chords": [
          {
            "root": 6,
            "beat": 1,
            "duration": 2,
            "type": 5,
            "inversion": 0,
            "applied": 0,
            "adds": [],
            "omits": [
              3,
              5
            ],
            "alterations": [],
            "suspensions": [],
            "substitutions": [],
            "pedal": null,
            "alternate": "",
            "borrowed": "",
            "isRest": false,
            "recordingEndBeat": null
          },
          {
            "root": 1,
            "beat": 3,
            "duration": 2,
            "type": 5,
            "inversion": 0,
            "applied": 0,
            "adds": [],
            "omits": [
              3,
              5
            ],
            "alterations": [],
            "suspensions": [],
            "substitutions": [],
            "pedal": null,
            "alternate": "",
            "borrowed": [
              -1,
              1,
              3,
              5,
              6,
              8,
              10
            ],
            "isRest": false,
            "recordingEndBeat": null
          },
          {
            "root": 1,
            "beat": 5,
            "duration": 2.5,
            "type": 5,
            "inversion": 0,
            "applied": 0,
            "adds": [],
            "omits": [
              3,
              5
            ],
            "alterations": [],
            "suspensions": [],
            "substitutions": [],
            "pedal": null,
            "alternate": "",
            "borrowed": "",
            "isRest": false,
            "recordingEndBeat": null
          },
          {
            "root": 3,
            "beat": 7.5,
            "duration": 1.5,
            "type": 5,
            "inversion": 0,
            "applied": 0,
            "adds": [],
            "omits": [],
            "alterations": [],
            "suspensions": [],
            "substitutions": [],
            "pedal": null,
            "alternate": "",
            "borrowed": "",
            "isRest": true,
            "recordingEndBeat": null
          },
          {
            "root": 6,
            "beat": 9,
            "duration": 2,
            "type": 5,
            "inversion": 0,
            "applied": 0,
            "adds": [],
            "omits": [
              3,
              5
            ],
            "alterations": [],
            "suspensions": [],
            "substitutions": [],
            "pedal": null,
            "alternate": "",
            "borrowed": "",
            "isRest": false,
            "recordingEndBeat": null
          },
          {
            "root": 1,
            "beat": 11,
            "duration": 2,
            "type": 5,
            "inversion": 0,
            "applied": 0,
            "adds": [],
            "omits": [
              3,
              5
            ],
            "alterations": [],
            "suspensions": [],
            "substitutions": [],
            "pedal": null,
            "alternate": "",
            "borrowed": [
              -1,
              1,
              3,
              5,
              6,
              8,
              10
            ],
            "isRest": false,
            "recordingEndBeat": null
          },
          {
            "root": 1,
            "beat": 13,
            "duration": 2.5,
            "type": 5,
            "inversion": 0,
            "applied": 0,
            "adds": [],
            "omits": [
              3,
              5
            ],
            "alterations": [],
            "suspensions": [],
            "substitutions": [],
            "pedal": null,
            "alternate": "",
            "borrowed": "",
            "isRest": false,
            "recordingEndBeat": null
          },
          {
            "root": 3,
            "beat": 15.5,
            "duration": 1.5,
            "type": 5,
            "inversion": 0,
            "applied": 0,
            "adds": [],
            "omits": [],
            "alterations": [],
            "suspensions": [],
            "substitutions": [],
            "pedal": null,
            "alternate": "",
            "borrowed": "",
            "isRest": true,
            "recordingEndBeat": null
          },
          {
            "root": 6,
            "beat": 17,
            "duration": 2,
            "type": 5,
            "inversion": 0,
            "applied": 0,
            "adds": [],
            "omits": [
              3,
              5
            ],
            "alterations": [],
            "suspensions": [],
            "substitutions": [],
            "pedal": null,
            "alternate": "",
            "borrowed": "",
            "isRest": false,
            "recordingEndBeat": null
          },
          {
            "root": 1,
            "beat": 19,
            "duration": 2,
            "type": 5,
            "inversion": 0,
            "applied": 0,
            "adds": [],
            "omits": [
              3,
              5
            ],
            "alterations": [],
            "suspensions": [],
            "substitutions": [],
            "pedal": null,
            "alternate": "",
            "borrowed": [
              -1,
              1,
              3,
              5,
              6,
              8,
              10
            ],
            "isRest": false,
            "recordingEndBeat": null
          },
          {
            "root": 1,
            "beat": 21,
            "duration": 2.5,
            "type": 5,
            "inversion": 0,
            "applied": 0,
            "adds": [],
            "omits": [
              3,
              5
            ],
            "alterations": [],
            "suspensions": [],
            "substitutions": [],
            "pedal": null,
            "alternate": "",
            "borrowed": "",
            "isRest": false,
            "recordingEndBeat": null
          },
          {
            "root": 3,
            "beat": 23.5,
            "duration": 1.5,
            "type": 5,
            "inversion": 0,
            "applied": 0,
            "adds": [],
            "omits": [],
            "alterations": [],
            "suspensions": [],
            "substitutions": [],
            "pedal": null,
            "alternate": "",
            "borrowed": "",
            "isRest": true,
            "recordingEndBeat": null
          },
          {
            "root": 6,
            "beat": 25,
            "duration": 2,
            "type": 5,
            "inversion": 0,
            "applied": 0,
            "adds": [],
            "omits": [
              3,
              5
            ],
            "alterations": [],
            "suspensions": [],
            "substitutions": [],
            "pedal": null,
            "alternate": "",
            "borrowed": "",
            "isRest": false,
            "recordingEndBeat": null
          },
          {
            "root": 1,
            "beat": 27,
            "duration": 2,
            "type": 5,
            "inversion": 0,
            "applied": 0,
            "adds": [],
            "omits": [
              3,
              5
            ],
            "alterations": [],
            "suspensions": [],
            "substitutions": [],
            "pedal": null,
            "alternate": "",
            "borrowed": [
              -1,
              1,
              3,
              5,
              6,
              8,
              10
            ],
            "isRest": false,
            "recordingEndBeat": null
          },
          {
            "root": 1,
            "beat": 29,
            "duration": 2.5,
            "type": 5,
            "inversion": 0,
            "applied": 0,
            "adds": [],
            "omits": [
              3,
              5
            ],
            "alterations": [],
            "suspensions": [],
            "substitutions": [],
            "pedal": null,
            "alternate": "",
            "borrowed": "",
            "isRest": false,
            "recordingEndBeat": null
          },
          {
            "root": 3,
            "beat": 31.5,
            "duration": 1.5,
            "type": 5,
            "inversion": 0,
            "applied": 0,
            "adds": [],
            "omits": [],
            "alterations": [],
            "suspensions": [],
            "substitutions": [],
            "pedal": null,
            "alternate": "",
            "borrowed": "",
            "isRest": true,
            "recordingEndBeat": null
          }
        ],
        "notes": [
          {
            "sd": "6",
            "octave": 0,
            "beat": 1,
            "duration": 0.5,
            "isRest": false,
            "recordingEndBeat": null
          },
          {
            "sd": "6",
            "octave": 0,
            "beat": 1.5,
            "duration": 0.5,
            "isRest": false,
            "recordingEndBeat": null
          },
          {
            "sd": "6",
            "octave": 0,
            "beat": 2,
            "duration": 0.5,
            "isRest": false,
            "recordingEndBeat": null
          },
          {
            "sd": "6",
            "octave": 0,
            "beat": 2.5,
            "duration": 0.5,
            "isRest": false,
            "recordingEndBeat": null
          },
          {
            "sd": "5",
            "octave": 0,
            "beat": 3,
            "duration": 0.5,
            "isRest": false,
            "recordingEndBeat": null
          },
          {
            "sd": "5",
            "octave": 0,
            "beat": 3.5,
            "duration": 0.5,
            "isRest": false,
            "recordingEndBeat": null
          },
          {
            "sd": "5",
            "octave": 0,
            "beat": 4,
            "duration": 0.5,
            "isRest": false,
            "recordingEndBeat": null
          },
          {
            "sd": "5",
            "octave": 0,
            "beat": 4.5,
            "duration": 0.5,
            "isRest": false,
            "recordingEndBeat": null
          },
          {
            "sd": "5",
            "octave": 0,
            "beat": 5,
            "duration": 0.5,
            "isRest": false,
            "recordingEndBeat": null
          },
          {
            "sd": "5",
            "octave": 0,
            "beat": 5.5,
            "duration": 0.5,
            "isRest": false,
            "recordingEndBeat": null
          },
          {
            "sd": "5",
            "octave": 0,
            "beat": 6,
            "duration": 0.5,
            "isRest": false,
            "recordingEndBeat": null
          },
          {
            "sd": "5",
            "octave": 0,
            "beat": 6.5,
            "duration": 0.5,
            "isRest": false,
            "recordingEndBeat": null
          },
          {
            "sd": "5",
            "octave": 0,
            "beat": 7,
            "duration": 0.5,
            "isRest": false,
            "recordingEndBeat": null
          },
          {
            "sd": "6",
            "octave": 0,
            "beat": 9,
            "duration": 0.5,
            "isRest": false,
            "recordingEndBeat": null
          },
          {
            "sd": "6",
            "octave": 0,
            "beat": 9.5,
            "duration": 0.5,
            "isRest": false,
            "recordingEndBeat": null
          },
          {
            "sd": "6",
            "octave": 0,
            "beat": 10,
            "duration": 0.5,
            "isRest": false,
            "recordingEndBeat": null
          },
          {
            "sd": "6",
            "octave": 0,
            "beat": 10.5,
            "duration": 0.5,
            "isRest": false,
            "recordingEndBeat": null
          },
          {
            "sd": "6",
            "octave": 0,
            "beat": 11,
            "duration": 0.5,
            "isRest": false,
            "recordingEndBeat": null
          },
          {
            "sd": "6",
            "octave": 0,
            "beat": 11.5,
            "duration": 0.5,
            "isRest": false,
            "recordingEndBeat": null
          },
          {
            "sd": "6",
            "octave": 0,
            "beat": 12,
            "duration": 0.5,
            "isRest": false,
            "recordingEndBeat": null
          },
          {
            "sd": "6",
            "octave": 0,
            "beat": 12.5,
            "duration": 0.5,
            "isRest": false,
            "recordingEndBeat": null
          },
          {
            "sd": "5",
            "octave": 0,
            "beat": 13,
            "duration": 0.5,
            "isRest": false,
            "recordingEndBeat": null
          },
          {
            "sd": "5",
            "octave": 0,
            "beat": 13.5,
            "duration": 0.5,
            "isRest": false,
            "recordingEndBeat": null
          },
          {
            "sd": "5",
            "octave": 0,
            "beat": 14,
            "duration": 0.5,
            "isRest": false,
            "recordingEndBeat": null
          },
          {
            "sd": "5",
            "octave": 0,
            "beat": 14.5,
            "duration": 0.5,
            "isRest": false,
            "recordingEndBeat": null
          },
          {
            "sd": "5",
            "octave": 0,
            "beat": 15,
            "duration": 0.5,
            "isRest": false,
            "recordingEndBeat": null
          },
          {
            "sd": "6",
            "octave": 0,
            "beat": 17,
            "duration": 0.5,
            "isRest": false,
            "recordingEndBeat": null
          },
          {
            "sd": "6",
            "octave": 0,
            "beat": 17.5,
            "duration": 0.5,
            "isRest": false,
            "recordingEndBeat": null
          },
          {
            "sd": "6",
            "octave": 0,
            "beat": 18,
            "duration": 0.5,
            "isRest": false,
            "recordingEndBeat": null
          },
          {
            "sd": "6",
            "octave": 0,
            "beat": 18.5,
            "duration": 0.5,
            "isRest": false,
            "recordingEndBeat": null
          },
          {
            "sd": "5",
            "octave": 0,
            "beat": 19,
            "duration": 0.5,
            "isRest": false,
            "recordingEndBeat": null
          },
          {
            "sd": "5",
            "octave": 0,
            "beat": 19.5,
            "duration": 0.5,
            "isRest": false,
            "recordingEndBeat": null
          },
          {
            "sd": "5",
            "octave": 0,
            "beat": 20,
            "duration": 0.5,
            "isRest": false,
            "recordingEndBeat": null
          },
          {
            "sd": "5",
            "octave": 0,
            "beat": 20.5,
            "duration": 0.5,
            "isRest": false,
            "recordingEndBeat": null
          },
          {
            "sd": "5",
            "octave": 0,
            "beat": 21,
            "duration": 0.5,
            "isRest": false,
            "recordingEndBeat": null
          },
          {
            "sd": "5",
            "octave": 0,
            "beat": 21.5,
            "duration": 0.5,
            "isRest": false,
            "recordingEndBeat": null
          },
          {
            "sd": "5",
            "octave": 0,
            "beat": 22,
            "duration": 0.5,
            "isRest": false,
            "recordingEndBeat": null
          },
          {
            "sd": "5",
            "octave": 0,
            "beat": 22.5,
            "duration": 0.5,
            "isRest": false,
            "recordingEndBeat": null
          },
          {
            "sd": "5",
            "octave": 0,
            "beat": 23,
            "duration": 0.5,
            "isRest": false,
            "recordingEndBeat": null
          },
          {
            "sd": "6",
            "octave": 0,
            "beat": 25,
            "duration": 0.5,
            "isRest": false,
            "recordingEndBeat": null
          },
          {
            "sd": "6",
            "octave": 0,
            "beat": 25.5,
            "duration": 0.5,
            "isRest": false,
            "recordingEndBeat": null
          },
          {
            "sd": "6",
            "octave": 0,
            "beat": 26,
            "duration": 0.5,
            "isRest": false,
            "recordingEndBeat": null
          },
          {
            "sd": "6",
            "octave": 0,
            "beat": 26.5,
            "duration": 0.5,
            "isRest": false,
            "recordingEndBeat": null
          },
          {
            "sd": "6",
            "octave": 0,
            "beat": 27,
            "duration": 0.5,
            "isRest": false,
            "recordingEndBeat": null
          },
          {
            "sd": "6",
            "octave": 0,
            "beat": 27.5,
            "duration": 0.5,
            "isRest": false,
            "recordingEndBeat": null
          },
          {
            "sd": "6",
            "octave": 0,
            "beat": 28,
            "duration": 0.5,
            "isRest": false,
            "recordingEndBeat": null
          },
          {
            "sd": "6",
            "octave": 0,
            "beat": 28.5,
            "duration": 0.5,
            "isRest": false,
            "recordingEndBeat": null
          },
          {
            "sd": "5",
            "octave": 0,
            "beat": 29,
            "duration": 0.5,
            "isRest": false,
            "recordingEndBeat": null
          },
          {
            "sd": "5",
            "octave": 0,
            "beat": 29.5,
            "duration": 0.5,
            "isRest": false,
            "recordingEndBeat": null
          },
          {
            "sd": "5",
            "octave": 0,
            "beat": 30,
            "duration": 0.5,
            "isRest": false,
            "recordingEndBeat": null
          },
          {
            "sd": "5",
            "octave": 0,
            "beat": 30.5,
            "duration": 0.5,
            "isRest": false,
            "recordingEndBeat": null
          },
          {
            "sd": "5",
            "octave": 0,
            "beat": 31,
            "duration": 0.5,
            "isRest": false,
            "recordingEndBeat": null
          }
        ],
        "metadata": {
          "version": "2.24.3",
          "keys": [
            {
              "beat": 1,
              "scale": "minor",
              "tonic": "E"
            }
          ],
          "tempos": [
            {
              "beat": 1,
              "bpm": 195,
              "swingFactor": 0,
              "swingBeat": 0.5
            }
          ],
          "meters": [
            {
              "beat": 1,
              "numBeats": 4,
              "beatUnit": 1
            }
          ],
          "sections": [],
          "endBeat": 33
        }
      },
      "rendered": [
        {
          "order": 0,
          "raw": "VI(no3no5)C(no3no5)",
          "stableX": 39,
          "texts": [
            {
              "s": "VI",
              "relX": 4,
              "y": 690,
              "fill": "#ffffff"
            },
            {
              "s": "(no3no5)",
              "relX": 26,
              "y": 693,
              "fill": "#ffffff"
            },
            {
              "s": "C",
              "relX": 14,
              "y": 726,
              "fill": "#dae0e6"
            },
            {
              "s": "(no3no5)",
              "relX": 25,
              "y": 726,
              "fill": "#dae0e6"
            }
          ],
          "pianoRaw": [
            {
              "stableX": 39,
              "sd": "6",
              "octave": "0",
              "cy": 607
            }
          ],
          "pianoNotes": null
        },
        {
          "order": 1,
          "raw": "bI(no3no5)(bor)Eb(no3no5)",
          "stableX": 111,
          "texts": [
            {
              "s": "bI",
              "relX": 10,
              "y": 690,
              "fill": "#ffffff"
            },
            {
              "s": "(no3no5)",
              "relX": 23,
              "y": 693,
              "fill": "#ffffff"
            },
            {
              "s": "(bor)",
              "relX": 26,
              "y": 705,
              "fill": "#ffffff"
            },
            {
              "s": "Eb",
              "relX": 13,
              "y": 728,
              "fill": "#dae0e6"
            },
            {
              "s": "(no3no5)",
              "relX": 28,
              "y": 727,
              "fill": "#dae0e6"
            }
          ],
          "pianoRaw": [
            {
              "stableX": 93,
              "sd": "6",
              "octave": "0",
              "cy": 607
            },
            {
              "stableX": 111,
              "sd": "5",
              "octave": "0",
              "cy": 618
            }
          ],
          "pianoNotes": [
            "B3",
            "C#4"
          ]
        },
        {
          "order": 2,
          "raw": "i(no3no5)em(no3no5)",
          "stableX": 183,
          "texts": [
            {
              "s": "i",
              "relX": 15,
              "y": 687,
              "fill": "#ffffff"
            },
            {
              "s": "(no3no5)",
              "relX": 22,
              "y": 691,
              "fill": "#ffffff"
            },
            {
              "s": "em",
              "relX": 17,
              "y": 727,
              "fill": "#dae0e6"
            },
            {
              "s": "(no3no5)",
              "relX": 40,
              "y": 726,
              "fill": "#dae0e6"
            }
          ],
          "pianoRaw": [
            {
              "stableX": 165,
              "sd": "5",
              "octave": "0",
              "cy": 618
            }
          ],
          "pianoNotes": null
        },
        {
          "order": 3,
          "raw": "VI(no3no5)C(no3no5)",
          "stableX": 327,
          "texts": [
            {
              "s": "VI",
              "relX": 4,
              "y": 690,
              "fill": "#ffffff"
            },
            {
              "s": "(no3no5)",
              "relX": 26,
              "y": 693,
              "fill": "#ffffff"
            },
            {
              "s": "C",
              "relX": 14,
              "y": 726,
              "fill": "#dae0e6"
            },
            {
              "s": "(no3no5)",
              "relX": 25,
              "y": 726,
              "fill": "#dae0e6"
            }
          ],
          "pianoRaw": [
            {
              "stableX": 327,
              "sd": "6",
              "octave": "0",
              "cy": 607
            }
          ],
          "pianoNotes": null
        },
        {
          "order": 4,
          "raw": "bI(no3no5)(bor)Eb(no3no5)",
          "stableX": 399,
          "texts": [
            {
              "s": "bI",
              "relX": 10,
              "y": 690,
              "fill": "#ffffff"
            },
            {
              "s": "(no3no5)",
              "relX": 23,
              "y": 693,
              "fill": "#ffffff"
            },
            {
              "s": "(bor)",
              "relX": 26,
              "y": 705,
              "fill": "#ffffff"
            },
            {
              "s": "Eb",
              "relX": 13,
              "y": 728,
              "fill": "#dae0e6"
            },
            {
              "s": "(no3no5)",
              "relX": 28,
              "y": 727,
              "fill": "#dae0e6"
            }
          ],
          "pianoRaw": [
            {
              "stableX": 381,
              "sd": "6",
              "octave": "0",
              "cy": 607
            }
          ],
          "pianoNotes": null
        },
        {
          "order": 5,
          "raw": "i(no3no5)em(no3no5)",
          "stableX": 471,
          "texts": [
            {
              "s": "i",
              "relX": 15,
              "y": 687,
              "fill": "#ffffff"
            },
            {
              "s": "(no3no5)",
              "relX": 22,
              "y": 691,
              "fill": "#ffffff"
            },
            {
              "s": "em",
              "relX": 17,
              "y": 727,
              "fill": "#dae0e6"
            },
            {
              "s": "(no3no5)",
              "relX": 40,
              "y": 726,
              "fill": "#dae0e6"
            }
          ],
          "pianoRaw": [
            {
              "stableX": 453,
              "sd": "6",
              "octave": "0",
              "cy": 607
            },
            {
              "stableX": 471,
              "sd": "5",
              "octave": "0",
              "cy": 618
            }
          ],
          "pianoNotes": [
            "B3",
            "C#4"
          ]
        },
        {
          "order": 6,
          "raw": "VI(no3no5)C(no3no5)",
          "stableX": 615,
          "texts": [
            {
              "s": "VI",
              "relX": 4,
              "y": 690,
              "fill": "#ffffff"
            },
            {
              "s": "(no3no5)",
              "relX": 26,
              "y": 693,
              "fill": "#ffffff"
            },
            {
              "s": "C",
              "relX": 14,
              "y": 726,
              "fill": "#dae0e6"
            },
            {
              "s": "(no3no5)",
              "relX": 25,
              "y": 726,
              "fill": "#dae0e6"
            }
          ],
          "pianoRaw": [
            {
              "stableX": 615,
              "sd": "6",
              "octave": "0",
              "cy": 607
            }
          ],
          "pianoNotes": null
        },
        {
          "order": 7,
          "raw": "bI(no3no5)(bor)Eb(no3no5)",
          "stableX": 687,
          "texts": [
            {
              "s": "bI",
              "relX": 10,
              "y": 690,
              "fill": "#ffffff"
            },
            {
              "s": "(no3no5)",
              "relX": 23,
              "y": 693,
              "fill": "#ffffff"
            },
            {
              "s": "(bor)",
              "relX": 26,
              "y": 705,
              "fill": "#ffffff"
            },
            {
              "s": "Eb",
              "relX": 13,
              "y": 728,
              "fill": "#dae0e6"
            },
            {
              "s": "(no3no5)",
              "relX": 28,
              "y": 727,
              "fill": "#dae0e6"
            }
          ],
          "pianoRaw": [
            {
              "stableX": 669,
              "sd": "6",
              "octave": "0",
              "cy": 607
            },
            {
              "stableX": 687,
              "sd": "5",
              "octave": "0",
              "cy": 618
            }
          ],
          "pianoNotes": [
            "B3",
            "C#4"
          ]
        },
        {
          "order": 8,
          "raw": "i(no3no5)em(no3no5)",
          "stableX": 759,
          "texts": [
            {
              "s": "i",
              "relX": 15,
              "y": 687,
              "fill": "#ffffff"
            },
            {
              "s": "(no3no5)",
              "relX": 22,
              "y": 691,
              "fill": "#ffffff"
            },
            {
              "s": "em",
              "relX": 17,
              "y": 727,
              "fill": "#dae0e6"
            },
            {
              "s": "(no3no5)",
              "relX": 40,
              "y": 726,
              "fill": "#dae0e6"
            }
          ],
          "pianoRaw": [
            {
              "stableX": 741,
              "sd": "5",
              "octave": "0",
              "cy": 618
            }
          ],
          "pianoNotes": null
        },
        {
          "order": 9,
          "raw": "VI(no3no5)C(no3no5)",
          "stableX": 903,
          "texts": [
            {
              "s": "VI",
              "relX": 4,
              "y": 690,
              "fill": "#ffffff"
            },
            {
              "s": "(no3no5)",
              "relX": 26,
              "y": 693,
              "fill": "#ffffff"
            },
            {
              "s": "C",
              "relX": 14,
              "y": 726,
              "fill": "#dae0e6"
            },
            {
              "s": "(no3no5)",
              "relX": 25,
              "y": 726,
              "fill": "#dae0e6"
            }
          ],
          "pianoRaw": [
            {
              "stableX": 903,
              "sd": "6",
              "octave": "0",
              "cy": 607
            }
          ],
          "pianoNotes": null
        },
        {
          "order": 10,
          "raw": "bI(no3no5)(bor)Eb(no3no5)",
          "stableX": 975,
          "texts": [
            {
              "s": "bI",
              "relX": 10,
              "y": 690,
              "fill": "#ffffff"
            },
            {
              "s": "(no3no5)",
              "relX": 23,
              "y": 693,
              "fill": "#ffffff"
            },
            {
              "s": "(bor)",
              "relX": 26,
              "y": 705,
              "fill": "#ffffff"
            },
            {
              "s": "Eb",
              "relX": 13,
              "y": 728,
              "fill": "#dae0e6"
            },
            {
              "s": "(no3no5)",
              "relX": 28,
              "y": 727,
              "fill": "#dae0e6"
            }
          ],
          "pianoRaw": [
            {
              "stableX": 957,
              "sd": "6",
              "octave": "0",
              "cy": 607
            }
          ],
          "pianoNotes": null
        },
        {
          "order": 11,
          "raw": "i(no3no5)em(no3no5)",
          "stableX": 1047,
          "texts": [
            {
              "s": "i",
              "relX": 15,
              "y": 687,
              "fill": "#ffffff"
            },
            {
              "s": "(no3no5)",
              "relX": 22,
              "y": 691,
              "fill": "#ffffff"
            },
            {
              "s": "em",
              "relX": 17,
              "y": 727,
              "fill": "#dae0e6"
            },
            {
              "s": "(no3no5)",
              "relX": 40,
              "y": 726,
              "fill": "#dae0e6"
            }
          ],
          "pianoRaw": [
            {
              "stableX": 1029,
              "sd": "6",
              "octave": "0",
              "cy": 607
            },
            {
              "stableX": 1047,
              "sd": "5",
              "octave": "0",
              "cy": 618
            }
          ],
          "pianoNotes": [
            "B3",
            "C#4"
          ]
        }
      ],
      "strips": []
    },
    {
      "name": "Chorus",
      "hash": "#chorus",
      "songId": "ZOxVMQdZgdq",
      "containerId": "tab-ZOxVMQdZgdq",
      "renderedCount": 10,
      "jsonChordCount": 11,
      "jsonNonRestCount": 10,
      "json": {
        "songId": 1347316,
        "songInfo": "Rated R Crusaders",
        "chords": [
          {
            "root": 6,
            "beat": 1,
            "duration": 2,
            "type": 5,
            "inversion": 0,
            "applied": 0,
            "adds": [],
            "omits": [
              3
            ],
            "alterations": [],
            "suspensions": [],
            "substitutions": [],
            "pedal": null,
            "alternate": "",
            "borrowed": "",
            "isRest": false,
            "recordingEndBeat": null
          },
          {
            "root": 1,
            "beat": 3,
            "duration": 2,
            "type": 5,
            "inversion": 0,
            "applied": 0,
            "adds": [],
            "omits": [
              3
            ],
            "alterations": [],
            "suspensions": [],
            "substitutions": [],
            "pedal": null,
            "alternate": "",
            "borrowed": [
              -1,
              1,
              3,
              5,
              6,
              8,
              10
            ],
            "isRest": false,
            "recordingEndBeat": null
          },
          {
            "root": 1,
            "beat": 5,
            "duration": 4,
            "type": 5,
            "inversion": 0,
            "applied": 0,
            "adds": [],
            "omits": [
              3
            ],
            "alterations": [],
            "suspensions": [],
            "substitutions": [],
            "pedal": null,
            "alternate": "",
            "borrowed": "",
            "isRest": false,
            "recordingEndBeat": null
          },
          {
            "root": 6,
            "beat": 9,
            "duration": 2,
            "type": 5,
            "inversion": 0,
            "applied": 0,
            "adds": [],
            "omits": [
              3
            ],
            "alterations": [],
            "suspensions": [],
            "substitutions": [],
            "pedal": null,
            "alternate": "",
            "borrowed": "",
            "isRest": false,
            "recordingEndBeat": null
          },
          {
            "root": 3,
            "beat": 11,
            "duration": 2,
            "type": 5,
            "inversion": 0,
            "applied": 0,
            "adds": [],
            "omits": [
              3
            ],
            "alterations": [],
            "suspensions": [],
            "substitutions": [],
            "pedal": null,
            "alternate": "",
            "borrowed": "",
            "isRest": false,
            "recordingEndBeat": null
          },
          {
            "root": 3,
            "beat": 13,
            "duration": 4,
            "type": 5,
            "inversion": 0,
            "applied": 0,
            "adds": [],
            "omits": [],
            "alterations": [],
            "suspensions": [],
            "substitutions": [],
            "pedal": null,
            "alternate": "",
            "borrowed": "",
            "isRest": true,
            "recordingEndBeat": null
          },
          {
            "root": 6,
            "beat": 17,
            "duration": 2,
            "type": 5,
            "inversion": 0,
            "applied": 0,
            "adds": [],
            "omits": [
              3
            ],
            "alterations": [],
            "suspensions": [],
            "substitutions": [],
            "pedal": null,
            "alternate": "",
            "borrowed": "",
            "isRest": false,
            "recordingEndBeat": null
          },
          {
            "root": 1,
            "beat": 19,
            "duration": 2,
            "type": 5,
            "inversion": 0,
            "applied": 0,
            "adds": [],
            "omits": [
              3
            ],
            "alterations": [],
            "suspensions": [],
            "substitutions": [],
            "pedal": null,
            "alternate": "",
            "borrowed": [
              -1,
              1,
              3,
              5,
              6,
              8,
              10
            ],
            "isRest": false,
            "recordingEndBeat": null
          },
          {
            "root": 1,
            "beat": 21,
            "duration": 4,
            "type": 5,
            "inversion": 0,
            "applied": 0,
            "adds": [],
            "omits": [
              3
            ],
            "alterations": [],
            "suspensions": [],
            "substitutions": [],
            "pedal": null,
            "alternate": "",
            "borrowed": "",
            "isRest": false,
            "recordingEndBeat": null
          },
          {
            "root": 6,
            "beat": 25,
            "duration": 4,
            "type": 5,
            "inversion": 0,
            "applied": 0,
            "adds": [],
            "omits": [],
            "alterations": [],
            "suspensions": [],
            "substitutions": [],
            "pedal": null,
            "alternate": "",
            "borrowed": "",
            "isRest": false,
            "recordingEndBeat": null
          },
          {
            "root": 5,
            "beat": 29,
            "duration": 4,
            "type": 5,
            "inversion": 0,
            "applied": 0,
            "adds": [],
            "omits": [],
            "alterations": [],
            "suspensions": [],
            "substitutions": [],
            "pedal": null,
            "alternate": "",
            "borrowed": "major",
            "isRest": false,
            "recordingEndBeat": null
          }
        ],
        "notes": [
          {
            "sd": "6",
            "octave": -1,
            "beat": 2,
            "duration": 1,
            "isRest": false,
            "recordingEndBeat": null
          },
          {
            "sd": "5",
            "octave": -1,
            "beat": 3,
            "duration": 1,
            "isRest": false,
            "recordingEndBeat": null
          },
          {
            "sd": "5",
            "octave": -1,
            "beat": 4,
            "duration": 1,
            "isRest": false,
            "recordingEndBeat": null
          },
          {
            "sd": "6",
            "octave": -1,
            "beat": 5,
            "duration": 1,
            "isRest": false,
            "recordingEndBeat": null
          },
          {
            "sd": "5",
            "octave": -1,
            "beat": 6,
            "duration": 1,
            "isRest": false,
            "recordingEndBeat": null
          },
          {
            "sd": "3",
            "octave": -1,
            "beat": 7,
            "duration": 1,
            "isRest": false,
            "recordingEndBeat": null
          },
          {
            "sd": "1",
            "octave": -1,
            "beat": 8,
            "duration": 1,
            "isRest": false,
            "recordingEndBeat": null
          },
          {
            "sd": "6",
            "octave": -1,
            "beat": 10,
            "duration": 1,
            "isRest": false,
            "recordingEndBeat": null
          },
          {
            "sd": "5",
            "octave": -1,
            "beat": 11,
            "duration": 1,
            "isRest": false,
            "recordingEndBeat": null
          },
          {
            "sd": "5",
            "octave": -1,
            "beat": 12,
            "duration": 1,
            "isRest": false,
            "recordingEndBeat": null
          },
          {
            "sd": "6",
            "octave": -1,
            "beat": 13,
            "duration": 1,
            "isRest": false,
            "recordingEndBeat": null
          },
          {
            "sd": "6",
            "octave": -1,
            "beat": 14,
            "duration": 1,
            "isRest": false,
            "recordingEndBeat": null
          },
          {
            "sd": "6",
            "octave": -1,
            "beat": 15,
            "duration": 1,
            "isRest": false,
            "recordingEndBeat": null
          },
          {
            "sd": "6",
            "octave": -1,
            "beat": 16,
            "duration": 1,
            "isRest": false,
            "recordingEndBeat": null
          },
          {
            "sd": "6",
            "octave": -1,
            "beat": 17,
            "duration": 1,
            "isRest": false,
            "recordingEndBeat": null
          },
          {
            "sd": "6",
            "octave": -1,
            "beat": 18,
            "duration": 1,
            "isRest": false,
            "recordingEndBeat": null
          },
          {
            "sd": "5",
            "octave": -1,
            "beat": 19,
            "duration": 1,
            "isRest": false,
            "recordingEndBeat": null
          },
          {
            "sd": "4",
            "octave": -1,
            "beat": 20,
            "duration": 1,
            "isRest": false,
            "recordingEndBeat": null
          },
          {
            "sd": "6",
            "octave": -1,
            "beat": 21,
            "duration": 1,
            "isRest": false,
            "recordingEndBeat": null
          },
          {
            "sd": "5",
            "octave": -1,
            "beat": 22,
            "duration": 1,
            "isRest": false,
            "recordingEndBeat": null
          },
          {
            "sd": "3",
            "octave": -1,
            "beat": 23,
            "duration": 1,
            "isRest": false,
            "recordingEndBeat": null
          },
          {
            "sd": "1",
            "octave": -1,
            "beat": 24,
            "duration": 1,
            "isRest": false,
            "recordingEndBeat": null
          },
          {
            "sd": "6",
            "octave": -1,
            "beat": 25,
            "duration": 1,
            "isRest": false,
            "recordingEndBeat": null
          },
          {
            "sd": "5",
            "octave": -1,
            "beat": 26,
            "duration": 0.5,
            "isRest": false,
            "recordingEndBeat": null
          },
          {
            "sd": "3",
            "octave": -1,
            "beat": 26.5,
            "duration": 1,
            "isRest": false,
            "recordingEndBeat": null
          },
          {
            "sd": "1",
            "octave": -1,
            "beat": 27.5,
            "duration": 0.5,
            "isRest": false,
            "recordingEndBeat": null
          },
          {
            "sd": "5",
            "octave": -1,
            "beat": 28.5,
            "duration": 1.5,
            "isRest": false,
            "recordingEndBeat": null
          },
          {
            "sd": "4",
            "octave": -1,
            "beat": 30,
            "duration": 0.5,
            "isRest": false,
            "recordingEndBeat": null
          },
          {
            "sd": "3",
            "octave": -1,
            "beat": 30.5,
            "duration": 1,
            "isRest": false,
            "recordingEndBeat": null
          },
          {
            "sd": "1",
            "octave": -1,
            "beat": 31.5,
            "duration": 0.5,
            "isRest": false,
            "recordingEndBeat": null
          },
          {
            "sd": "3",
            "octave": -1,
            "beat": 32,
            "duration": 0.5,
            "isRest": false,
            "recordingEndBeat": null
          },
          {
            "sd": "1",
            "octave": -1,
            "beat": 32.5,
            "duration": 0.5,
            "isRest": false,
            "recordingEndBeat": null
          }
        ],
        "metadata": {
          "version": "2.24.3",
          "keys": [
            {
              "beat": 1,
              "scale": "minor",
              "tonic": "E"
            }
          ],
          "tempos": [
            {
              "beat": 1,
              "bpm": 192,
              "swingFactor": 0,
              "swingBeat": 0.5
            }
          ],
          "meters": [
            {
              "beat": 1,
              "numBeats": 4,
              "beatUnit": 1
            }
          ],
          "sections": [],
          "endBeat": 33
        }
      },
      "rendered": [
        {
          "order": 0,
          "raw": "VI(no3)C5",
          "stableX": 39,
          "texts": [
            {
              "s": "VI",
              "relX": 5,
              "y": 764,
              "fill": "#ffffff"
            },
            {
              "s": "(no3)",
              "relX": 33,
              "y": 768,
              "fill": "#ffffff"
            },
            {
              "s": "C5",
              "relX": 24,
              "y": 803,
              "fill": "#dae0e6"
            }
          ],
          "pianoRaw": [],
          "pianoNotes": null
        },
        {
          "order": 1,
          "raw": "bI(no3)(bor)Eb5",
          "stableX": 111,
          "texts": [
            {
              "s": "bI",
              "relX": 15,
              "y": 765,
              "fill": "#ffffff"
            },
            {
              "s": "(no3)",
              "relX": 30,
              "y": 769,
              "fill": "#ffffff"
            },
            {
              "s": "(bor)",
              "relX": 25,
              "y": 784,
              "fill": "#ffffff"
            },
            {
              "s": "Eb5",
              "relX": 22,
              "y": 803,
              "fill": "#dae0e6"
            }
          ],
          "pianoRaw": [
            {
              "stableX": 111,
              "sd": "5",
              "octave": "-1",
              "cy": 695
            }
          ],
          "pianoNotes": null
        },
        {
          "order": 2,
          "raw": "i(no3)E5",
          "stableX": 183,
          "texts": [
            {
              "s": "i",
              "relX": 52,
              "y": 764,
              "fill": "#ffffff"
            },
            {
              "s": "(no3)",
              "relX": 59,
              "y": 768,
              "fill": "#ffffff"
            },
            {
              "s": "E5",
              "relX": 61,
              "y": 803,
              "fill": "#dae0e6"
            }
          ],
          "pianoRaw": [
            {
              "stableX": 183,
              "sd": "6",
              "octave": "-1",
              "cy": 684
            }
          ],
          "pianoNotes": null
        },
        {
          "order": 3,
          "raw": "VI(no3)C5",
          "stableX": 327,
          "texts": [
            {
              "s": "VI",
              "relX": 5,
              "y": 764,
              "fill": "#ffffff"
            },
            {
              "s": "(no3)",
              "relX": 33,
              "y": 768,
              "fill": "#ffffff"
            },
            {
              "s": "C5",
              "relX": 24,
              "y": 803,
              "fill": "#dae0e6"
            }
          ],
          "pianoRaw": [],
          "pianoNotes": null
        },
        {
          "order": 4,
          "raw": "III(no3)G5",
          "stableX": 399,
          "texts": [
            {
              "s": "III",
              "relX": 7,
              "y": 764,
              "fill": "#ffffff"
            },
            {
              "s": "(no3)",
              "relX": 33,
              "y": 768,
              "fill": "#ffffff"
            },
            {
              "s": "G5",
              "relX": 24,
              "y": 803,
              "fill": "#dae0e6"
            }
          ],
          "pianoRaw": [
            {
              "stableX": 399,
              "sd": "5",
              "octave": "-1",
              "cy": 695
            }
          ],
          "pianoNotes": null
        },
        {
          "order": 5,
          "raw": "VI(no3)C5",
          "stableX": 615,
          "texts": [
            {
              "s": "VI",
              "relX": 5,
              "y": 764,
              "fill": "#ffffff"
            },
            {
              "s": "(no3)",
              "relX": 33,
              "y": 768,
              "fill": "#ffffff"
            },
            {
              "s": "C5",
              "relX": 24,
              "y": 803,
              "fill": "#dae0e6"
            }
          ],
          "pianoRaw": [
            {
              "stableX": 615,
              "sd": "6",
              "octave": "-1",
              "cy": 684
            }
          ],
          "pianoNotes": null
        },
        {
          "order": 6,
          "raw": "bI(no3)(bor)Eb5",
          "stableX": 687,
          "texts": [
            {
              "s": "bI",
              "relX": 15,
              "y": 765,
              "fill": "#ffffff"
            },
            {
              "s": "(no3)",
              "relX": 30,
              "y": 769,
              "fill": "#ffffff"
            },
            {
              "s": "(bor)",
              "relX": 25,
              "y": 784,
              "fill": "#ffffff"
            },
            {
              "s": "Eb5",
              "relX": 22,
              "y": 803,
              "fill": "#dae0e6"
            }
          ],
          "pianoRaw": [
            {
              "stableX": 687,
              "sd": "5",
              "octave": "-1",
              "cy": 695
            }
          ],
          "pianoNotes": null
        },
        {
          "order": 7,
          "raw": "i(no3)E5",
          "stableX": 759,
          "texts": [
            {
              "s": "i",
              "relX": 52,
              "y": 764,
              "fill": "#ffffff"
            },
            {
              "s": "(no3)",
              "relX": 59,
              "y": 768,
              "fill": "#ffffff"
            },
            {
              "s": "E5",
              "relX": 61,
              "y": 803,
              "fill": "#dae0e6"
            }
          ],
          "pianoRaw": [
            {
              "stableX": 759,
              "sd": "6",
              "octave": "-1",
              "cy": 684
            }
          ],
          "pianoNotes": null
        },
        {
          "order": 8,
          "raw": "VIC",
          "stableX": 903,
          "texts": [
            {
              "s": "VI",
              "relX": 56,
              "y": 764,
              "fill": "#ffffff"
            },
            {
              "s": "C",
              "relX": 65,
              "y": 803,
              "fill": "#dae0e6"
            }
          ],
          "pianoRaw": [
            {
              "stableX": 903,
              "sd": "6",
              "octave": "-1",
              "cy": 684
            }
          ],
          "pianoNotes": null
        },
        {
          "order": 9,
          "raw": "V(maj)B",
          "stableX": 1047,
          "texts": [
            {
              "s": "V",
              "relX": 63,
              "y": 766,
              "fill": "#ffffff"
            },
            {
              "s": "(maj)",
              "relX": 60,
              "y": 784,
              "fill": "#ffffff"
            },
            {
              "s": "B",
              "relX": 65,
              "y": 803,
              "fill": "#dae0e6"
            }
          ],
          "pianoRaw": [
            {
              "stableX": 1029,
              "sd": "5",
              "octave": "-1",
              "cy": 695
            }
          ],
          "pianoNotes": null
        }
      ],
      "strips": []
    }
  ],
  "errors": []
}