[
  {
    "id": "lady-gaga__bad-romance/Chorus/3",
    "song": "lady-gaga__bad-romance",
    "section": "Chorus",
    "beat": 3,
    "key": {
      "tonic": "A",
      "scale": "minor"
    },
    "chord": {
      "root": 6,
      "beat": 3,
      "duration": 2,
      "type": 5,
      "inversion": 0,
      "applied": 0,
      "adds": [
        9
      ],
      "omits": [],
      "alterations": [],
      "suspensions": [],
      "substitutions": [],
      "pedal": null,
      "alternate": "",
      "borrowed": null,
      "isRest": false,
      "recordingEndBeat": null
    },
    "truthRoman": "VI(add9)",
    "truthLetter": "F(add9)",
    "truthPcs": [
      0,
      5,
      7,
      9
    ],
    "pianoNotes": null,
    "pianoPcs": null,
    "pianoValidated": false,
    "engRoman": "VI(add9)",
    "engLetter": "F",
    "engNotes": [
      "F3",
      "A3",
      "C4",
      "G4"
    ],
    "engPcs": [
      0,
      5,
      7,
      9
    ],
    "flags": {
      "romanExact": true,
      "romanCore": true,
      "rootPcMatch": true,
      "bassPcMatch": false,
      "rootInPcs": true,
      "bassInNotes": true,
      "pcsExact": true,
      "pianoExact": false,
      "pianoPcsExact": false,
      "pianoValidated": false,
      "usePiano": false,
      "orderOk": true,
      "degreesOk": true
    },
    "notesOk": true,
    "orderOk": true,
    "romanExact": true,
    "failureClass": null,
    "buckets": [
      "type=5",
      "inversion=0",
      "applied=no",
      "borrowed=none",
      "adds=9"
    ],
    "compositeKey": null
  },
  {
    "id": "lady-gaga__bad-romance/Chorus/15",
    "song": "lady-gaga__bad-romance",
    "section": "Chorus",
    "beat": 15,
    "key": {
      "tonic": "A",
      "scale": "minor"
    },
    "chord": {
      "root": 3,
      "beat": 15,
      "duration": 1,
      "type": 5,
      "inversion": 0,
      "applied": 0,
      "adds": [
        9
      ],
      "omits": [],
      "alterations": [],
      "suspensions": [],
      "substitutions": [],
      "pedal": null,
      "alternate": "",
      "borrowed": "",
      "isRest": false,
      "recordingEndBeat": null
    },
    "truthRoman": "III(add9)",
    "truthLetter": "C(add9)",
    "truthPcs": [
      0,
      2,
      4,
      7
    ],
    "pianoNotes": null,
    "pianoPcs": null,
    "pianoValidated": false,
    "engRoman": "III(add9)",
    "engLetter": "C",
    "engNotes": [
      "C3",
      "E3",
      "G3",
      "D4"
    ],
    "engPcs": [
      0,
      2,
      4,
      7
    ],
    "flags": {
      "romanExact": true,
      "romanCore": true,
      "rootPcMatch": true,
      "bassPcMatch": false,
      "rootInPcs": true,
      "bassInNotes": true,
      "pcsExact": true,
      "pianoExact": false,
      "pianoPcsExact": false,
      "pianoValidated": false,
      "usePiano": false,
      "orderOk": true,
      "degreesOk": true
    },
    "notesOk": true,
    "orderOk": true,
    "romanExact": true,
    "failureClass": null,
    "buckets": [
      "type=5",
      "inversion=0",
      "applied=no",
      "borrowed=none",
      "adds=9"
    ],
    "compositeKey": null
  },
  {
    "id": "lady-gaga__bad-romance/Chorus/19",
    "song": "lady-gaga__bad-romance",
    "section": "Chorus",
    "beat": 19,
    "key": {
      "tonic": "A",
      "scale": "minor"
    },
    "chord": {
      "root": 6,
      "beat": 19,
      "duration": 2,
      "type": 5,
      "inversion": 0,
      "applied": 0,
      "adds": [
        9
      ],
      "omits": [],
      "alterations": [],
      "suspensions": [],
      "substitutions": [],
      "pedal": null,
      "alternate": "",
      "borrowed": null,
      "isRest": false,
      "recordingEndBeat": null
    },
    "truthRoman": "VI(add9)",
    "truthLetter": "F(add9)",
    "truthPcs": [
      0,
      5,
      7,
      9
    ],
    "pianoNotes": null,
    "pianoPcs": null,
    "pianoValidated": false,
    "engRoman": "VI(add9)",
    "engLetter": "F",
    "engNotes": [
      "F3",
      "A3",
      "C4",
      "G4"
    ],
    "engPcs": [
      0,
      5,
      7,
      9
    ],
    "flags": {
      "romanExact": true,
      "romanCore": true,
      "rootPcMatch": true,
      "bassPcMatch": false,
      "rootInPcs": true,
      "bassInNotes": true,
      "pcsExact": true,
      "pianoExact": false,
      "pianoPcsExact": false,
      "pianoValidated": false,
      "usePiano": false,
      "orderOk": true,
      "degreesOk": true
    },
    "notesOk": true,
    "orderOk": true,
    "romanExact": true,
    "failureClass": null,
    "buckets": [
      "type=5",
      "inversion=0",
      "applied=no",
      "borrowed=none",
      "adds=9"
    ],
    "compositeKey": null
  },
  {
    "id": "lady-gaga__bad-romance/Chorus/31",
    "song": "lady-gaga__bad-romance",
    "section": "Chorus",
    "beat": 31,
    "key": {
      "tonic": "A",
      "scale": "minor"
    },
    "chord": {
      "root": 3,
      "beat": 31,
      "duration": 1,
      "type": 5,
      "inversion": 0,
      "applied": 0,
      "adds": [
        9
      ],
      "omits": [],
      "alterations": [],
      "suspensions": [],
      "substitutions": [],
      "pedal": null,
      "alternate": "",
      "borrowed": "",
      "isRest": false,
      "recordingEndBeat": null
    },
    "truthRoman": "III(add9)",
    "truthLetter": "C(add9)",
    "truthPcs": [
      0,
      2,
      4,
      7
    ],
    "pianoNotes": [
      "E2",
      "F2"
    ],
    "pianoPcs": [
      4,
      5
    ],
    "pianoValidated": false,
    "engRoman": "III(add9)",
    "engLetter": "C",
    "engNotes": [
      "C3",
      "E3",
      "G3",
      "D4"
    ],
    "engPcs": [
      0,
      2,
      4,
      7
    ],
    "flags": {
      "romanExact": true,
      "romanCore": true,
      "rootPcMatch": true,
      "bassPcMatch": false,
      "rootInPcs": true,
      "bassInNotes": true,
      "pcsExact": true,
      "pianoExact": false,
      "pianoPcsExact": false,
      "pianoValidated": false,
      "usePiano": false,
      "orderOk": true,
      "degreesOk": true
    },
    "notesOk": true,
    "orderOk": true,
    "romanExact": true,
    "failureClass": null,
    "buckets": [
      "type=5",
      "inversion=0",
      "applied=no",
      "borrowed=none",
      "adds=9"
    ],
    "compositeKey": null
  },
  {
    "id": "lady-gaga__bad-romance/Chorus/35",
    "song": "lady-gaga__bad-romance",
    "section": "Chorus",
    "beat": 35,
    "key": {
      "tonic": "A",
      "scale": "minor"
    },
    "chord": {
      "root": 6,
      "beat": 35,
      "duration": 2,
      "type": 5,
      "inversion": 0,
      "applied": 0,
      "adds": [
        9
      ],
      "omits": [],
      "alterations": [],
      "suspensions": [],
      "substitutions": [],
      "pedal": null,
      "alternate": "",
      "borrowed": null,
      "isRest": false,
      "recordingEndBeat": null
    },
    "truthRoman": "VI(add9)",
    "truthLetter": "F(add9)",
    "truthPcs": [
      0,
      5,
      7,
      9
    ],
    "pianoNotes": [
      "C3",
      "D3"
    ],
    "pianoPcs": [
      0,
      2
    ],
    "pianoValidated": false,
    "engRoman": "VI(add9)",
    "engLetter": "F",
    "engNotes": [
      "F3",
      "A3",
      "C4",
      "G4"
    ],
    "engPcs": [
      0,
      5,
      7,
      9
    ],
    "flags": {
      "romanExact": true,
      "romanCore": true,
      "rootPcMatch": true,
      "bassPcMatch": false,
      "rootInPcs": true,
      "bassInNotes": true,
      "pcsExact": true,
      "pianoExact": false,
      "pianoPcsExact": false,
      "pianoValidated": false,
      "usePiano": false,
      "orderOk": true,
      "degreesOk": true
    },
    "notesOk": true,
    "orderOk": true,
    "romanExact": true,
    "failureClass": null,
    "buckets": [
      "type=5",
      "inversion=0",
      "applied=no",
      "borrowed=none",
      "adds=9"
    ],
    "compositeKey": null
  },
  {
    "id": "lady-gaga__bad-romance/Chorus/47",
    "song": "lady-gaga__bad-romance",
    "section": "Chorus",
    "beat": 47,
    "key": {
      "tonic": "A",
      "scale": "minor"
    },
    "chord": {
      "root": 3,
      "beat": 47,
      "duration": 1,
      "type": 5,
      "inversion": 0,
      "applied": 0,
      "adds": [
        9
      ],
      "omits": [],
      "alterations": [],
      "suspensions": [],
      "substitutions": [],
      "pedal": null,
      "alternate": "",
      "borrowed": "",
      "isRest": false,
      "recordingEndBeat": null
    },
    "truthRoman": "III(add9)",
    "truthLetter": "C(add9)",
    "truthPcs": [
      0,
      2,
      4,
      7
    ],
    "pianoNotes": [
      "E2",
      "F2"
    ],
    "pianoPcs": [
      4,
      5
    ],
    "pianoValidated": false,
    "engRoman": "III(add9)",
    "engLetter": "C",
    "engNotes": [
      "C3",
      "E3",
      "G3",
      "D4"
    ],
    "engPcs": [
      0,
      2,
      4,
      7
    ],
    "flags": {
      "romanExact": true,
      "romanCore": true,
      "rootPcMatch": true,
      "bassPcMatch": false,
      "rootInPcs": true,
      "bassInNotes": true,
      "pcsExact": true,
      "pianoExact": false,
      "pianoPcsExact": false,
      "pianoValidated": false,
      "usePiano": false,
      "orderOk": true,
      "degreesOk": true
    },
    "notesOk": true,
    "orderOk": true,
    "romanExact": true,
    "failureClass": null,
    "buckets": [
      "type=5",
      "inversion=0",
      "applied=no",
      "borrowed=none",
      "adds=9"
    ],
    "compositeKey": null
  },
  {
    "id": "lady-gaga__bad-romance/Chorus/51",
    "song": "lady-gaga__bad-romance",
    "section": "Chorus",
    "beat": 51,
    "key": {
      "tonic": "A",
      "scale": "minor"
    },
    "chord": {
      "root": 6,
      "beat": 51,
      "duration": 2,
      "type": 5,
      "inversion": 0,
      "applied": 0,
      "adds": [
        9
      ],
      "omits": [],
      "alterations": [],
      "suspensions": [],
      "substitutions": [],
      "pedal": null,
      "alternate": "",
      "borrowed": null,
      "isRest": false,
      "recordingEndBeat": null
    },
    "truthRoman": "VI(add9)",
    "truthLetter": "F(add9)",
    "truthPcs": [
      0,
      5,
      7,
      9
    ],
    "pianoNotes": [
      "C3",
      "D3"
    ],
    "pianoPcs": [
      0,
      2
    ],
    "pianoValidated": false,
    "engRoman": "VI(add9)",
    "engLetter": "F",
    "engNotes": [
      "F3",
      "A3",
      "C4",
      "G4"
    ],
    "engPcs": [
      0,
      5,
      7,
      9
    ],
    "flags": {
      "romanExact": true,
      "romanCore": true,
      "rootPcMatch": true,
      "bassPcMatch": false,
      "rootInPcs": true,
      "bassInNotes": true,
      "pcsExact": true,
      "pianoExact": false,
      "pianoPcsExact": false,
      "pianoValidated": false,
      "usePiano": false,
      "orderOk": true,
      "degreesOk": true
    },
    "notesOk": true,
    "orderOk": true,
    "romanExact": true,
    "failureClass": null,
    "buckets": [
      "type=5",
      "inversion=0",
      "applied=no",
      "borrowed=none",
      "adds=9"
    ],
    "compositeKey": null
  },
  {
    "id": "lady-gaga__bad-romance/Chorus/63",
    "song": "lady-gaga__bad-romance",
    "section": "Chorus",
    "beat": 63,
    "key": {
      "tonic": "A",
      "scale": "minor"
    },
    "chord": {
      "root": 3,
      "beat": 63,
      "duration": 1,
      "type": 5,
      "inversion": 0,
      "applied": 0,
      "adds": [
        9
      ],
      "omits": [],
      "alterations": [],
      "suspensions": [],
      "substitutions": [],
      "pedal": null,
      "alternate": "",
      "borrowed": "",
      "isRest": false,
      "recordingEndBeat": null
    },
    "truthRoman": "III(add9)",
    "truthLetter": "C(add9)",
    "truthPcs": [
      0,
      2,
      4,
      7
    ],
    "pianoNotes": null,
    "pianoPcs": null,
    "pianoValidated": false,
    "engRoman": "III(add9)",
    "engLetter": "C",
    "engNotes": [
      "C3",
      "E3",
      "G3",
      "D4"
    ],
    "engPcs": [
      0,
      2,
      4,
      7
    ],
    "flags": {
      "romanExact": true,
      "romanCore": true,
      "rootPcMatch": true,
      "bassPcMatch": false,
      "rootInPcs": true,
      "bassInNotes": true,
      "pcsExact": true,
      "pianoExact": false,
      "pianoPcsExact": false,
      "pianoValidated": false,
      "usePiano": false,
      "orderOk": true,
      "degreesOk": true
    },
    "notesOk": true,
    "orderOk": true,
    "romanExact": true,
    "failureClass": null,
    "buckets": [
      "type=5",
      "inversion=0",
      "applied=no",
      "borrowed=none",
      "adds=9"
    ],
    "compositeKey": null
  }
]