{
  "url": "https://www.hooktheory.com/theorytab/view/joseph-haydn/12-easy-pieces-for-piano-no-1---andante-grazioso",
  "title": "12 Easy Pieces for Piano No 1 - Andante Grazioso by Joseph Haydn Chords, Melody, and Music Theory Analysis - Hooktheory",
  "sections": [
    {
      "name": "Intro",
      "hash": "#intro",
      "songId": "JkmZZbMbmqn",
      "containerId": "tab-JkmZZbMbmqn",
      "renderedCount": 25,
      "jsonChordCount": 26,
      "jsonNonRestCount": 25,
      "json": {
        "songId": 1231610,
        "songInfo": "12 Easy Pieces for Piano No 1 - Andante Grazioso",
        "chords": [
          {
            "root": 1,
            "beat": 1,
            "duration": 1,
            "type": 5,
            "inversion": 0,
            "applied": 0,
            "adds": [],
            "omits": [],
            "alterations": [],
            "suspensions": [],
            "pedal": null,
            "alternate": "",
            "borrowed": "",
            "isRest": false,
            "recordingEndBeat": null
          },
          {
            "root": 1,
            "beat": 2,
            "duration": 1,
            "type": 5,
            "inversion": 1,
            "applied": 0,
            "adds": [],
            "omits": [],
            "alterations": [],
            "suspensions": [],
            "pedal": null,
            "alternate": "",
            "borrowed": "",
            "isRest": false,
            "recordingEndBeat": null
          },
          {
            "root": 6,
            "beat": 3,
            "duration": 1,
            "type": 5,
            "inversion": 1,
            "applied": 5,
            "adds": [],
            "omits": [],
            "alterations": [
              "#5"
            ],
            "suspensions": [],
            "pedal": null,
            "alternate": "",
            "borrowed": "",
            "isRest": false,
            "recordingEndBeat": null
          },
          {
            "root": 6,
            "beat": 4,
            "duration": 1,
            "type": 5,
            "inversion": 0,
            "applied": 0,
            "adds": [],
            "omits": [],
            "alterations": [],
            "suspensions": [],
            "pedal": null,
            "alternate": "",
            "borrowed": "",
            "isRest": false,
            "recordingEndBeat": null
          },
          {
            "root": 2,
            "beat": 5,
            "duration": 3,
            "type": 5,
            "inversion": 1,
            "applied": 0,
            "adds": [],
            "omits": [],
            "alterations": [],
            "suspensions": [],
            "pedal": null,
            "alternate": "",
            "borrowed": "",
            "isRest": false,
            "recordingEndBeat": null
          },
          {
            "root": 5,
            "beat": 8,
            "duration": 1,
            "type": 5,
            "inversion": 0,
            "applied": 0,
            "adds": [],
            "omits": [],
            "alterations": [],
            "suspensions": [],
            "pedal": null,
            "alternate": "",
            "borrowed": "",
            "isRest": false,
            "recordingEndBeat": null
          },
          {
            "root": 1,
            "beat": 9,
            "duration": 1,
            "type": 5,
            "inversion": 1,
            "applied": 0,
            "adds": [],
            "omits": [],
            "alterations": [],
            "suspensions": [],
            "pedal": null,
            "alternate": "",
            "borrowed": "",
            "isRest": false,
            "recordingEndBeat": null
          },
          {
            "root": 2,
            "beat": 10,
            "duration": 1,
            "type": 7,
            "inversion": 1,
            "applied": 7,
            "adds": [],
            "omits": [],
            "alterations": [],
            "suspensions": [],
            "pedal": null,
            "alternate": "",
            "borrowed": "",
            "isRest": false,
            "recordingEndBeat": null
          },
          {
            "root": 2,
            "beat": 11,
            "duration": 2,
            "type": 5,
            "inversion": 0,
            "applied": 0,
            "adds": [],
            "omits": [],
            "alterations": [],
            "suspensions": [],
            "pedal": null,
            "alternate": "",
            "borrowed": "",
            "isRest": false,
            "recordingEndBeat": null
          },
          {
            "root": 1,
            "beat": 13,
            "duration": 2,
            "type": 5,
            "inversion": 2,
            "applied": 0,
            "adds": [],
            "omits": [],
            "alterations": [],
            "suspensions": [],
            "pedal": null,
            "alternate": "",
            "borrowed": "",
            "isRest": false,
            "recordingEndBeat": null
          },
          {
            "root": 5,
            "beat": 15,
            "duration": 0.5,
            "type": 5,
            "inversion": 0,
            "applied": 0,
            "adds": [],
            "omits": [],
            "alterations": [],
            "suspensions": [],
            "pedal": null,
            "alternate": "",
            "borrowed": "",
            "isRest": false,
            "recordingEndBeat": null
          },
          {
            "root": 1,
            "beat": 15.5,
            "duration": 1.5,
            "type": 5,
            "inversion": 0,
            "applied": 0,
            "adds": [],
            "omits": [],
            "alterations": [],
            "suspensions": [],
            "pedal": null,
            "alternate": "",
            "borrowed": "",
            "isRest": true,
            "recordingEndBeat": null
          },
          {
            "root": 1,
            "beat": 17,
            "duration": 1,
            "type": 5,
            "inversion": 0,
            "applied": 0,
            "adds": [],
            "omits": [],
            "alterations": [],
            "suspensions": [],
            "pedal": null,
            "alternate": "",
            "borrowed": "",
            "isRest": false,
            "recordingEndBeat": null
          },
          {
            "root": 1,
            "beat": 18,
            "duration": 1,
            "type": 5,
            "inversion": 1,
            "applied": 0,
            "adds": [],
            "omits": [],
            "alterations": [],
            "suspensions": [],
            "pedal": null,
            "alternate": "",
            "borrowed": "",
            "isRest": false,
            "recordingEndBeat": null
          },
          {
            "root": 6,
            "beat": 19,
            "duration": 1,
            "type": 5,
            "inversion": 1,
            "applied": 5,
            "adds": [],
            "omits": [],
            "alterations": [
              "#5"
            ],
            "suspensions": [],
            "pedal": null,
            "alternate": "",
            "borrowed": "",
            "isRest": false,
            "recordingEndBeat": null
          },
          {
            "root": 6,
            "beat": 20,
            "duration": 1,
            "type": 5,
            "inversion": 0,
            "applied": 0,
            "adds": [],
            "omits": [],
            "alterations": [],
            "suspensions": [],
            "pedal": null,
            "alternate": "",
            "borrowed": "",
            "isRest": false,
            "recordingEndBeat": null
          },
          {
            "root": 3,
            "beat": 21,
            "duration": 1,
            "type": 7,
            "inversion": 1,
            "applied": 7,
            "adds": [],
            "omits": [],
            "alterations": [],
            "suspensions": [],
            "pedal": null,
            "alternate": "",
            "borrowed": "",
            "isRest": false,
            "recordingEndBeat": null
          },
          {
            "root": 3,
            "beat": 22,
            "duration": 1,
            "type": 7,
            "inversion": 2,
            "applied": 7,
            "adds": [],
            "omits": [],
            "alterations": [],
            "suspensions": [],
            "pedal": null,
            "alternate": "",
            "borrowed": "",
            "isRest": false,
            "recordingEndBeat": null
          },
          {
            "root": 3,
            "beat": 23,
            "duration": 1,
            "type": 7,
            "inversion": 3,
            "applied": 7,
            "adds": [],
            "omits": [],
            "alterations": [],
            "suspensions": [],
            "pedal": null,
            "alternate": "",
            "borrowed": "",
            "isRest": false,
            "recordingEndBeat": null
          },
          {
            "root": 3,
            "beat": 24,
            "duration": 1,
            "type": 7,
            "inversion": 0,
            "applied": 7,
            "adds": [],
            "omits": [],
            "alterations": [],
            "suspensions": [],
            "pedal": null,
            "alternate": "",
            "borrowed": "",
            "isRest": false,
            "recordingEndBeat": null
          },
          {
            "root": 6,
            "beat": 25,
            "duration": 1,
            "type": 5,
            "inversion": 0,
            "applied": 0,
            "adds": [],
            "omits": [],
            "alterations": [],
            "suspensions": [],
            "pedal": null,
            "alternate": "",
            "borrowed": "",
            "isRest": false,
            "recordingEndBeat": null
          },
          {
            "root": 2,
            "beat": 26,
            "duration": 1,
            "type": 7,
            "inversion": 0,
            "applied": 5,
            "adds": [],
            "omits": [],
            "alterations": [],
            "suspensions": [],
            "pedal": null,
            "alternate": "",
            "borrowed": "phrygian",
            "isRest": false,
            "recordingEndBeat": null
          },
          {
            "root": 1,
            "beat": 27,
            "duration": 1,
            "type": 5,
            "inversion": 2,
            "applied": 0,
            "adds": [],
            "omits": [],
            "alterations": [],
            "suspensions": [],
            "pedal": null,
            "alternate": "",
            "borrowed": "",
            "isRest": false,
            "recordingEndBeat": null
          },
          {
            "root": 5,
            "beat": 28,
            "duration": 1,
            "type": 7,
            "inversion": 0,
            "applied": 0,
            "adds": [],
            "omits": [],
            "alterations": [],
            "suspensions": [],
            "pedal": null,
            "alternate": "",
            "borrowed": "",
            "isRest": false,
            "recordingEndBeat": null
          },
          {
            "root": 1,
            "beat": 29,
            "duration": 2,
            "type": 7,
            "inversion": 0,
            "applied": 0,
            "adds": [],
            "omits": [],
            "alterations": [],
            "suspensions": [
              2,
              4
            ],
            "pedal": null,
            "alternate": "",
            "borrowed": "",
            "isRest": false,
            "recordingEndBeat": null
          },
          {
            "root": 1,
            "beat": 31,
            "duration": 1,
            "type": 5,
            "inversion": 0,
            "applied": 0,
            "adds": [],
            "omits": [],
            "alterations": [],
            "suspensions": [],
            "pedal": null,
            "alternate": "",
            "borrowed": "",
            "isRest": false,
            "recordingEndBeat": null
          }
        ],
        "notes": [
          {
            "sd": "5",
            "octave": 0,
            "beat": 1,
            "duration": 1.75,
            "isRest": false,
            "recordingEndBeat": null
          },
          {
            "sd": "4",
            "octave": 0,
            "beat": 2.75,
            "duration": 0.25,
            "isRest": false,
            "recordingEndBeat": null
          },
          {
            "sd": "3",
            "octave": 0,
            "beat": 3,
            "duration": 1,
            "isRest": false,
            "recordingEndBeat": null
          },
          {
            "sd": "3",
            "octave": 0,
            "beat": 4,
            "duration": 1,
            "isRest": false,
            "recordingEndBeat": null
          },
          {
            "sd": "3",
            "octave": 0,
            "beat": 5,
            "duration": 1,
            "isRest": false,
            "recordingEndBeat": null
          },
          {
            "sd": "4",
            "octave": 0,
            "beat": 6,
            "duration": 1,
            "isRest": false,
            "recordingEndBeat": null
          },
          {
            "sd": "2",
            "octave": 0,
            "beat": 7,
            "duration": 2,
            "isRest": false,
            "recordingEndBeat": null
          },
          {
            "sd": "1",
            "octave": 0,
            "beat": 9,
            "duration": 1,
            "isRest": false,
            "recordingEndBeat": null
          },
          {
            "sd": "#1",
            "octave": 0,
            "beat": 10,
            "duration": 1,
            "isRest": false,
            "recordingEndBeat": null
          },
          {
            "sd": "2",
            "octave": 0,
            "beat": 11,
            "duration": 0.75,
            "isRest": false,
            "recordingEndBeat": null
          },
          {
            "sd": "3",
            "octave": 0,
            "beat": 11.75,
            "duration": 0.25,
            "isRest": false,
            "recordingEndBeat": null
          },
          {
            "sd": "4",
            "octave": 0,
            "beat": 12,
            "duration": 0.75,
            "isRest": false,
            "recordingEndBeat": null
          },
          {
            "sd": "6",
            "octave": 0,
            "beat": 12.75,
            "duration": 0.25,
            "isRest": false,
            "recordingEndBeat": null
          },
          {
            "sd": "3",
            "octave": 0,
            "beat": 13,
            "duration": 2,
            "isRest": false,
            "recordingEndBeat": null
          },
          {
            "sd": "2",
            "octave": 0,
            "beat": 15,
            "duration": 0.5,
            "isRest": false,
            "recordingEndBeat": null
          },
          {
            "sd": "3",
            "octave": 0,
            "beat": 15.5,
            "duration": 0.5,
            "isRest": false,
            "recordingEndBeat": null
          },
          {
            "sd": "4",
            "octave": 0,
            "beat": 16,
            "duration": 0.5,
            "isRest": false,
            "recordingEndBeat": null
          },
          {
            "sd": "#4",
            "octave": 0,
            "beat": 16.5,
            "duration": 0.5,
            "isRest": false,
            "recordingEndBeat": null
          },
          {
            "sd": "5",
            "octave": 0,
            "beat": 17,
            "duration": 1.75,
            "isRest": false,
            "recordingEndBeat": null
          },
          {
            "sd": "4",
            "octave": 0,
            "beat": 18.75,
            "duration": 0.25,
            "isRest": false,
            "recordingEndBeat": null
          },
          {
            "sd": "3",
            "octave": 0,
            "beat": 19,
            "duration": 1,
            "isRest": false,
            "recordingEndBeat": null
          },
          {
            "sd": "3",
            "octave": 0,
            "beat": 20,
            "duration": 1,
            "isRest": false,
            "recordingEndBeat": null
          },
          {
            "sd": "6",
            "octave": 0,
            "beat": 21,
            "duration": 1.75,
            "isRest": false,
            "recordingEndBeat": null
          },
          {
            "sd": "5",
            "octave": 0,
            "beat": 22.75,
            "duration": 0.25,
            "isRest": false,
            "recordingEndBeat": null
          },
          {
            "sd": "#4",
            "octave": 0,
            "beat": 23,
            "duration": 1,
            "isRest": false,
            "recordingEndBeat": null
          },
          {
            "sd": "b5",
            "octave": 0,
            "beat": 24,
            "duration": 1,
            "isRest": false,
            "recordingEndBeat": null
          },
          {
            "sd": "1",
            "octave": 1,
            "beat": 25,
            "duration": 1,
            "isRest": false,
            "recordingEndBeat": null
          },
          {
            "sd": "#4",
            "octave": 0,
            "beat": 26,
            "duration": 1,
            "isRest": false,
            "recordingEndBeat": null
          },
          {
            "sd": "5",
            "octave": 0,
            "beat": 27,
            "duration": 1,
            "isRest": false,
            "recordingEndBeat": null
          },
          {
            "sd": "7",
            "octave": -1,
            "beat": 28,
            "duration": 1,
            "isRest": false,
            "recordingEndBeat": null
          },
          {
            "sd": "2",
            "octave": 0,
            "beat": 29,
            "duration": 2,
            "isRest": false,
            "recordingEndBeat": null
          },
          {
            "sd": "1",
            "octave": 0,
            "beat": 31,
            "duration": 1,
            "isRest": false,
            "recordingEndBeat": null
          }
        ],
        "metadata": {
          "version": "2.24.3",
          "keys": [
            {
              "beat": 1,
              "scale": "major",
              "tonic": "Bb"
            },
            {
              "beat": 25,
              "scale": "major",
              "tonic": "F"
            }
          ],
          "tempos": [
            {
              "beat": 1,
              "bpm": 80,
              "swingFactor": 0,
              "swingBeat": 0.5
            }
          ],
          "meters": [
            {
              "beat": 1,
              "numBeats": 4,
              "beatUnit": 1
            }
          ],
          "sections": [],
          "endBeat": 33
        }
      },
      "rendered": [
        {
          "order": 0,
          "raw": "IBb",
          "stableX": 39,
          "texts": [
            {
              "s": "I",
              "relX": 13,
              "y": 741,
              "fill": "#ffffff"
            },
            {
              "s": "Bb",
              "relX": 8,
              "y": 780,
              "fill": "#dae0e6"
            }
          ],
          "pianoRaw": [
            {
              "stableX": 39,
              "sd": "5",
              "octave": "0",
              "cy": 628
            }
          ],
          "pianoNotes": null
        },
        {
          "order": 1,
          "raw": "I6Bb/D",
          "stableX": 75,
          "texts": [
            {
              "s": "I",
              "relX": 9,
              "y": 741,
              "fill": "#ffffff"
            },
            {
              "s": "6",
              "relX": 18,
              "y": 745,
              "fill": "#ffffff"
            },
            {
              "s": "Bb",
              "relX": 7,
              "y": 785,
              "fill": "#dae0e6"
            },
            {
              "s": "/D",
              "relX": 15,
              "y": 785,
              "fill": "#dae0e6"
            }
          ],
          "pianoRaw": [],
          "pianoNotes": null
        },
        {
          "order": 2,
          "raw": "V+6(#5)/viD++(#5)/F#",
          "stableX": 111,
          "texts": [
            {
              "s": "V",
              "relX": 2,
              "y": 751,
              "fill": "#ffffff"
            },
            {
              "s": "+6(#5)",
              "relX": 8,
              "y": 752,
              "fill": "#ffffff"
            },
            {
              "s": "/",
              "relX": 19,
              "y": 751,
              "fill": "#ffffff"
            },
            {
              "s": "vi",
              "relX": 24,
              "y": 751,
              "fill": "#ffffff"
            },
            {
              "s": "D+",
              "relX": 7,
              "y": 786,
              "fill": "#dae0e6"
            },
            {
              "s": "+",
              "relX": 11,
              "y": 786,
              "fill": "#dae0e6"
            },
            {
              "s": "(#5)",
              "relX": 12,
              "y": 786,
              "fill": "#dae0e6"
            },
            {
              "s": "/F#",
              "relX": 17,
              "y": 786,
              "fill": "#dae0e6"
            }
          ],
          "pianoRaw": [
            {
              "stableX": 102,
              "sd": "4",
              "octave": "0",
              "cy": 639
            },
            {
              "stableX": 111,
              "sd": "3",
              "octave": "0",
              "cy": 650
            }
          ],
          "pianoNotes": [
            "F#3",
            "G3"
          ]
        },
        {
          "order": 3,
          "raw": "vigm",
          "stableX": 147,
          "texts": [
            {
              "s": "vi",
              "relX": 6,
              "y": 741,
              "fill": "#ffffff"
            },
            {
              "s": "gm",
              "relX": 7,
              "y": 782,
              "fill": "#dae0e6"
            }
          ],
          "pianoRaw": [
            {
              "stableX": 147,
              "sd": "3",
              "octave": "0",
              "cy": 650
            }
          ],
          "pianoNotes": null
        },
        {
          "order": 4,
          "raw": "ii6cm/Eb",
          "stableX": 183,
          "texts": [
            {
              "s": "ii",
              "relX": 42,
              "y": 741,
              "fill": "#ffffff"
            },
            {
              "s": "6",
              "relX": 57,
              "y": 745,
              "fill": "#ffffff"
            },
            {
              "s": "cm",
              "relX": 28,
              "y": 780,
              "fill": "#dae0e6"
            },
            {
              "s": "/Eb",
              "relX": 52,
              "y": 780,
              "fill": "#dae0e6"
            }
          ],
          "pianoRaw": [
            {
              "stableX": 183,
              "sd": "3",
              "octave": "0",
              "cy": 650
            }
          ],
          "pianoNotes": null
        },
        {
          "order": 5,
          "raw": "VF",
          "stableX": 291,
          "texts": [
            {
              "s": "V",
              "relX": 7,
              "y": 741,
              "fill": "#ffffff"
            },
            {
              "s": "F",
              "relX": 12,
              "y": 780,
              "fill": "#dae0e6"
            }
          ],
          "pianoRaw": [],
          "pianoNotes": null
        },
        {
          "order": 6,
          "raw": "I6Bb/D",
          "stableX": 327,
          "texts": [
            {
              "s": "I",
              "relX": 9,
              "y": 741,
              "fill": "#ffffff"
            },
            {
              "s": "6",
              "relX": 18,
              "y": 745,
              "fill": "#ffffff"
            },
            {
              "s": "Bb",
              "relX": 7,
              "y": 785,
              "fill": "#dae0e6"
            },
            {
              "s": "/D",
              "relX": 15,
              "y": 785,
              "fill": "#dae0e6"
            }
          ],
          "pianoRaw": [
            {
              "stableX": 327,
              "sd": "1",
              "octave": "0",
              "cy": 672
            }
          ],
          "pianoNotes": null
        },
        {
          "order": 7,
          "raw": "vii°65/iibo7o/D",
          "stableX": 363,
          "texts": [
            {
              "s": "vii",
              "relX": 2,
              "y": 750,
              "fill": "#ffffff"
            },
            {
              "s": "°6",
              "relX": 14,
              "y": 751,
              "fill": "#ffffff"
            },
            {
              "s": "5",
              "relX": 15,
              "y": 755,
              "fill": "#ffffff"
            },
            {
              "s": "/",
              "relX": 18,
              "y": 750,
              "fill": "#ffffff"
            },
            {
              "s": "ii",
              "relX": 25,
              "y": 750,
              "fill": "#ffffff"
            },
            {
              "s": "bo7",
              "relX": 6,
              "y": 785,
              "fill": "#dae0e6"
            },
            {
              "s": "o",
              "relX": 10,
              "y": 784,
              "fill": "#dae0e6"
            },
            {
              "s": "/D",
              "relX": 16,
              "y": 785,
              "fill": "#dae0e6"
            }
          ],
          "pianoRaw": [
            {
              "stableX": 363,
              "sd": "#1",
              "octave": "0",
              "cy": 667
            }
          ],
          "pianoNotes": null
        },
        {
          "order": 8,
          "raw": "iicm",
          "stableX": 399,
          "texts": [
            {
              "s": "ii",
              "relX": 28,
              "y": 741,
              "fill": "#ffffff"
            },
            {
              "s": "cm",
              "relX": 23,
              "y": 780,
              "fill": "#dae0e6"
            }
          ],
          "pianoRaw": [
            {
              "stableX": 399,
              "sd": "2",
              "octave": "0",
              "cy": 661
            }
          ],
          "pianoNotes": null
        },
        {
          "order": 9,
          "raw": "I64Bb/F",
          "stableX": 471,
          "texts": [
            {
              "s": "I",
              "relX": 27,
              "y": 741,
              "fill": "#ffffff"
            },
            {
              "s": "6",
              "relX": 36,
              "y": 745,
              "fill": "#ffffff"
            },
            {
              "s": "4",
              "relX": 36,
              "y": 754,
              "fill": "#ffffff"
            },
            {
              "s": "Bb",
              "relX": 17,
              "y": 780,
              "fill": "#dae0e6"
            },
            {
              "s": "/F",
              "relX": 33,
              "y": 780,
              "fill": "#dae0e6"
            }
          ],
          "pianoRaw": [
            {
              "stableX": 462,
              "sd": "6",
              "octave": "0",
              "cy": 617
            },
            {
              "stableX": 471,
              "sd": "3",
              "octave": "0",
              "cy": 650
            }
          ],
          "pianoNotes": [
            "D4",
            "G4"
          ]
        },
        {
          "order": 10,
          "raw": "VF",
          "stableX": 543,
          "texts": [
            {
              "s": "V",
              "relX": 1,
              "y": 747,
              "fill": "#ffffff"
            },
            {
              "s": "F",
              "relX": 4,
              "y": 782,
              "fill": "#dae0e6"
            }
          ],
          "pianoRaw": [
            {
              "stableX": 543,
              "sd": "2",
              "octave": "0",
              "cy": 661
            },
            {
              "stableX": 561,
              "sd": "3",
              "octave": "0",
              "cy": 650
            }
          ],
          "pianoNotes": [
            "G3",
            "A3"
          ]
        },
        {
          "order": 11,
          "raw": "IBb",
          "stableX": 615,
          "texts": [
            {
              "s": "I",
              "relX": 13,
              "y": 741,
              "fill": "#ffffff"
            },
            {
              "s": "Bb",
              "relX": 8,
              "y": 780,
              "fill": "#dae0e6"
            }
          ],
          "pianoRaw": [
            {
              "stableX": 597,
              "sd": "#4",
              "octave": "0",
              "cy": 634
            },
            {
              "stableX": 615,
              "sd": "5",
              "octave": "0",
              "cy": 628
            }
          ],
          "pianoNotes": [
            "E4",
            "F4"
          ]
        },
        {
          "order": 12,
          "raw": "I6Bb/D",
          "stableX": 651,
          "texts": [
            {
              "s": "I",
              "relX": 9,
              "y": 741,
              "fill": "#ffffff"
            },
            {
              "s": "6",
              "relX": 18,
              "y": 745,
              "fill": "#ffffff"
            },
            {
              "s": "Bb",
              "relX": 7,
              "y": 785,
              "fill": "#dae0e6"
            },
            {
              "s": "/D",
              "relX": 15,
              "y": 785,
              "fill": "#dae0e6"
            }
          ],
          "pianoRaw": [],
          "pianoNotes": null
        },
        {
          "order": 13,
          "raw": "V+6(#5)/viD++(#5)/F#",
          "stableX": 687,
          "texts": [
            {
              "s": "V",
              "relX": 2,
              "y": 751,
              "fill": "#ffffff"
            },
            {
              "s": "+6(#5)",
              "relX": 8,
              "y": 752,
              "fill": "#ffffff"
            },
            {
              "s": "/",
              "relX": 19,
              "y": 751,
              "fill": "#ffffff"
            },
            {
              "s": "vi",
              "relX": 24,
              "y": 751,
              "fill": "#ffffff"
            },
            {
              "s": "D+",
              "relX": 7,
              "y": 786,
              "fill": "#dae0e6"
            },
            {
              "s": "+",
              "relX": 11,
              "y": 786,
              "fill": "#dae0e6"
            },
            {
              "s": "(#5)",
              "relX": 12,
              "y": 786,
              "fill": "#dae0e6"
            },
            {
              "s": "/F#",
              "relX": 17,
              "y": 786,
              "fill": "#dae0e6"
            }
          ],
          "pianoRaw": [
            {
              "stableX": 678,
              "sd": "4",
              "octave": "0",
              "cy": 639
            },
            {
              "stableX": 687,
              "sd": "3",
              "octave": "0",
              "cy": 650
            }
          ],
          "pianoNotes": [
            "F#3",
            "G3"
          ]
        },
        {
          "order": 14,
          "raw": "vigm",
          "stableX": 723,
          "texts": [
            {
              "s": "vi",
              "relX": 6,
              "y": 741,
              "fill": "#ffffff"
            },
            {
              "s": "gm",
              "relX": 7,
              "y": 782,
              "fill": "#dae0e6"
            }
          ],
          "pianoRaw": [
            {
              "stableX": 723,
              "sd": "3",
              "octave": "0",
              "cy": 650
            }
          ],
          "pianoNotes": null
        },
        {
          "order": 15,
          "raw": "vii°65/iiic#o7o/E",
          "stableX": 759,
          "texts": [
            {
              "s": "vii",
              "relX": 2,
              "y": 751,
              "fill": "#ffffff"
            },
            {
              "s": "°6",
              "relX": 13,
              "y": 751,
              "fill": "#ffffff"
            },
            {
              "s": "5",
              "relX": 14,
              "y": 755,
              "fill": "#ffffff"
            },
            {
              "s": "/",
              "relX": 17,
              "y": 750,
              "fill": "#ffffff"
            },
            {
              "s": "iii",
              "relX": 23,
              "y": 751,
              "fill": "#ffffff"
            },
            {
              "s": "c#o7",
              "relX": 7,
              "y": 785,
              "fill": "#dae0e6"
            },
            {
              "s": "o",
              "relX": 13,
              "y": 786,
              "fill": "#dae0e6"
            },
            {
              "s": "/E",
              "relX": 18,
              "y": 785,
              "fill": "#dae0e6"
            }
          ],
          "pianoRaw": [
            {
              "stableX": 759,
              "sd": "6",
              "octave": "0",
              "cy": 617
            }
          ],
          "pianoNotes": null
        },
        {
          "order": 16,
          "raw": "vii°43/iiic#o7o/G",
          "stableX": 795,
          "texts": [
            {
              "s": "vii",
              "relX": 2,
              "y": 751,
              "fill": "#ffffff"
            },
            {
              "s": "°4",
              "relX": 13,
              "y": 751,
              "fill": "#ffffff"
            },
            {
              "s": "3",
              "relX": 14,
              "y": 755,
              "fill": "#ffffff"
            },
            {
              "s": "/",
              "relX": 17,
              "y": 751,
              "fill": "#ffffff"
            },
            {
              "s": "iii",
              "relX": 23,
              "y": 751,
              "fill": "#ffffff"
            },
            {
              "s": "c#o7",
              "relX": 7,
              "y": 785,
              "fill": "#dae0e6"
            },
            {
              "s": "o",
              "relX": 13,
              "y": 786,
              "fill": "#dae0e6"
            },
            {
              "s": "/G",
              "relX": 18,
              "y": 785,
              "fill": "#dae0e6"
            }
          ],
          "pianoRaw": [],
          "pianoNotes": null
        },
        {
          "order": 17,
          "raw": "vii°42/iiic#oo/Bb",
          "stableX": 831,
          "texts": [
            {
              "s": "vii",
              "relX": 2,
              "y": 751,
              "fill": "#ffffff"
            },
            {
              "s": "°4",
              "relX": 13,
              "y": 751,
              "fill": "#ffffff"
            },
            {
              "s": "2",
              "relX": 14,
              "y": 755,
              "fill": "#ffffff"
            },
            {
              "s": "/",
              "relX": 17,
              "y": 751,
              "fill": "#ffffff"
            },
            {
              "s": "iii",
              "relX": 23,
              "y": 751,
              "fill": "#ffffff"
            },
            {
              "s": "c#o",
              "relX": 7,
              "y": 786,
              "fill": "#dae0e6"
            },
            {
              "s": "o",
              "relX": 14,
              "y": 785,
              "fill": "#dae0e6"
            },
            {
              "s": "/Bb",
              "relX": 15,
              "y": 786,
              "fill": "#dae0e6"
            }
          ],
          "pianoRaw": [
            {
              "stableX": 822,
              "sd": "5",
              "octave": "0",
              "cy": 628
            },
            {
              "stableX": 831,
              "sd": "#4",
              "octave": "0",
              "cy": 634
            }
          ],
          "pianoNotes": null
        },
        {
          "order": 18,
          "raw": "vii°7/iiic#o7o",
          "stableX": 867,
          "texts": [
            {
              "s": "vii",
              "relX": 2,
              "y": 751,
              "fill": "#ffffff"
            },
            {
              "s": "°7",
              "relX": 13,
              "y": 751,
              "fill": "#ffffff"
            },
            {
              "s": "/",
              "relX": 16,
              "y": 750,
              "fill": "#ffffff"
            },
            {
              "s": "iii",
              "relX": 23,
              "y": 751,
              "fill": "#ffffff"
            },
            {
              "s": "c#o7",
              "relX": 7,
              "y": 783,
              "fill": "#dae0e6"
            },
            {
              "s": "o",
              "relX": 18,
              "y": 783,
              "fill": "#dae0e6"
            }
          ],
          "pianoRaw": [
            {
              "stableX": 867,
              "sd": "b5",
              "octave": "0",
              "cy": 634
            }
          ],
          "pianoNotes": null
        },
        {
          "order": 19,
          "raw": "vidm",
          "stableX": 953,
          "texts": [
            {
              "s": "vi",
              "relX": 6,
              "y": 741,
              "fill": "#ffffff"
            },
            {
              "s": "dm",
              "relX": 7,
              "y": 782,
              "fill": "#dae0e6"
            }
          ],
          "pianoRaw": [
            {
              "stableX": 953,
              "sd": "1",
              "octave": "1",
              "cy": 628
            }
          ],
          "pianoNotes": null
        },
        {
          "order": 20,
          "raw": "V7/bII(phr)Db7",
          "stableX": 989,
          "texts": [
            {
              "s": "V",
              "relX": 5,
              "y": 750,
              "fill": "#ffffff"
            },
            {
              "s": "7",
              "relX": 12,
              "y": 752,
              "fill": "#ffffff"
            },
            {
              "s": "/",
              "relX": 13,
              "y": 750,
              "fill": "#ffffff"
            },
            {
              "s": "bII",
              "relX": 18,
              "y": 750,
              "fill": "#ffffff"
            },
            {
              "s": "(phr)",
              "relX": 18,
              "y": 757,
              "fill": "#ffffff"
            },
            {
              "s": "Db7",
              "relX": 7,
              "y": 783,
              "fill": "#dae0e6"
            }
          ],
          "pianoRaw": [
            {
              "stableX": 989,
              "sd": "#4",
              "octave": "0",
              "cy": 667
            }
          ],
          "pianoNotes": null
        },
        {
          "order": 21,
          "raw": "I64F/C",
          "stableX": 1025,
          "texts": [
            {
              "s": "I",
              "relX": 9,
              "y": 741,
              "fill": "#ffffff"
            },
            {
              "s": "6",
              "relX": 18,
              "y": 745,
              "fill": "#ffffff"
            },
            {
              "s": "4",
              "relX": 18,
              "y": 754,
              "fill": "#ffffff"
            },
            {
              "s": "F",
              "relX": 7,
              "y": 784,
              "fill": "#dae0e6"
            },
            {
              "s": "/C",
              "relX": 13,
              "y": 784,
              "fill": "#dae0e6"
            }
          ],
          "pianoRaw": [
            {
              "stableX": 1025,
              "sd": "5",
              "octave": "0",
              "cy": 661
            }
          ],
          "pianoNotes": null
        },
        {
          "order": 22,
          "raw": "V7C7",
          "stableX": 1061,
          "texts": [
            {
              "s": "V",
              "relX": 3,
              "y": 741,
              "fill": "#ffffff"
            },
            {
              "s": "7",
              "relX": 23,
              "y": 745,
              "fill": "#ffffff"
            },
            {
              "s": "C7",
              "relX": 7,
              "y": 781,
              "fill": "#dae0e6"
            }
          ],
          "pianoRaw": [
            {
              "stableX": 1061,
              "sd": "7",
              "octave": "-1",
              "cy": 716
            }
          ],
          "pianoNotes": null
        },
        {
          "order": 23,
          "raw": "I7sus2sus4F7sus2sus4",
          "stableX": 1097,
          "texts": [
            {
              "s": "I",
              "relX": 6,
              "y": 741,
              "fill": "#ffffff"
            },
            {
              "s": "7",
              "relX": 14,
              "y": 745,
              "fill": "#ffffff"
            },
            {
              "s": "sus2sus4",
              "relX": 14,
              "y": 754,
              "fill": "#ffffff"
            },
            {
              "s": "F7",
              "relX": 14,
              "y": 782,
              "fill": "#dae0e6"
            },
            {
              "s": "sus2sus4",
              "relX": 31,
              "y": 786,
              "fill": "#dae0e6"
            }
          ],
          "pianoRaw": [
            {
              "stableX": 1097,
              "sd": "2",
              "octave": "0",
              "cy": 694
            }
          ],
          "pianoNotes": null
        },
        {
          "order": 24,
          "raw": "IF",
          "stableX": 1169,
          "texts": [
            {
              "s": "I",
              "relX": 13,
              "y": 741,
              "fill": "#ffffff"
            },
            {
              "s": "F",
              "relX": 12,
              "y": 780,
              "fill": "#dae0e6"
            }
          ],
          "pianoRaw": [
            {
              "stableX": 1169,
              "sd": "1",
              "octave": "0",
              "cy": 705
            }
          ],
          "pianoNotes": null
        }
      ],
      "strips": []
    }
  ],
  "errors": []
}